uart_reciever/uart_reciever.srcs/sources_1/new/hex_to_7seg.v
`timescale 1ns / 1ps
//////////////////////////////////////////////////////////////////////////////////
// Company: 
// Engineer: 
// 
// Create Date: 02/28/2025 05:30:32 PM
// Design Name: 
// Module Name: hex_to_7seg
// Project Name: 
// Target Devices: 
// Tool Versions: 
// Description: 
// 
// Dependencies: 
// 
// Revision:
// Revision 0.01 - File Created
// Additional Comments:
// 
//////////////////////////////////////////////////////////////////////////////////

module hex_to_7seg(
    input [3:0] hex,
    output reg [6:0] seg
);
    always @(*) begin
        case (hex)
             4'b0000: seg = 7'b0000001; // "0"  
             4'b0001: seg = 7'b1001111; // "1" 
             4'b0010: seg = 7'b0010010; // "2" 
             4'b0011: seg = 7'b0000110; // "3" 
             4'b0100: seg = 7'b1001100; // "4" 
             4'b0101: seg = 7'b0100100; // "5" 
             4'b0110: seg = 7'b0100000; // "6" 
             4'b0111: seg = 7'b0001111; // "7" 
             4'b1000: seg = 7'b0000000; // "8"  
             4'b1001: seg = 7'b0000100; // "9" 
             default: seg = 7'b0000001; // "0"
        endcase
    end
endmodule

uart_reciever/uart_reciever.srcs/sources_1/new/binary_to_bcd.v
`timescale 1ns / 1ps
//////////////////////////////////////////////////////////////////////////////////
// Company: 
// Engineer: 
// 
// Create Date: 02/28/2025 05:26:00 PM
// Design Name: 
// Module Name: binary_to_bcd
// Project Name: 
// Target Devices: 
// Tool Versions: 
// Description: 
// 
// Dependencies: 
// 
// Revision:
// Revision 0.01 - File Created
// Additional Comments:
// 
//////////////////////////////////////////////////////////////////////////////////
`timescale 1ns / 1ps

module bin2bcd(
    bin,
     hundreds,
     tens,
     ones
    );

    
    //input ports and their sizes
    input [7:0] bin;
    //output ports and, their size
    output [3:0] hundreds, tens,ones;
    //Internal variables
    reg [11 : 0] bcd; 
     reg [3:0] i;   
     
     //Always block - implement the Double Dabble algorithm
     always @(bin)
        begin
            bcd = 0; //initialize bcd to zero.
            for (i = 0; i < 8; i = i+1) //run for 8 iterations
            begin
                bcd = {bcd[10:0],bin[7-i]}; //concatenation
                    
                //if a hex digit of 'bcd' is more than 4, add 3 to it.  
                if(i < 7 && bcd[3:0] > 4) 
                    bcd[3:0] = bcd[3:0] + 3;
                if(i < 7 && bcd[7:4] > 4)
                    bcd[7:4] = bcd[7:4] + 3;
                if(i < 7 && bcd[11:8] > 4)
                    bcd[11:8] = bcd[11:8] + 3;  
            end
        end     
        assign hundreds = bcd [11:8];
        assign tens = bcd [7:4];
        assign ones = bcd [3:0];       
endmodule

uart_reciever/uart_reciever.srcs/sources_1/new/clk_divider.v
`timescale 1ns / 1ps
//////////////////////////////////////////////////////////////////////////////////
// Company: 
// Engineer: 
// 
// Create Date: 02/28/2025 05:31:26 PM
// Design Name: 
// Module Name: clk_divider
// Project Name: 
// Target Devices: 
// Tool Versions: 
// Description: 
// 
// Dependencies: 
// 
// Revision:
// Revision 0.01 - File Created
// Additional Comments:
// 
//////////////////////////////////////////////////////////////////////////////////


module clk_divider(
    input clk, // 100MHz FPGA Clock
    output slow_clk // Slower clock for display multiplexing
);
    reg [16:0] count = 0; // Large counter for dividing clock speed

    always @(posedge clk) begin
        count <= count + 1;
    end
    assign slow_clk = count[16];
endmodule

uart_reciever/uart_reciever.srcs/sources_1/new/seg_display_driver.v
`timescale 1ns / 1ps
//////////////////////////////////////////////////////////////////////////////////
// Company: 
// Engineer: 
// 
// Create Date: 02/28/2025 05:16:06 PM
// Design Name: 
// Module Name: seg_display_driver
// Project Name: 
// Target Devices: 
// Tool Versions: 
// Description: 
// 
// Dependencies: 
// 
// Revision:
// Revision 0.01 - File Created
// Additional Comments:
// 
//////////////////////////////////////////////////////////////////////////////////


module seg_display_driver(
    input [7:0] output_data_0,
    input clk,
    output reg [3:0] an,   // Selects which digit is active
    output reg [6:0] seg   // Segments for the active digit

    );

    wire slow_clk;
    reg [1:0] select_digit ; // Multiplexer selector
    wire [6:0] seg_hundreds, seg_tens, seg_ones;
    wire [3:0] hundreds, tens, ones;

    initial begin
        select_digit= 0;
    end
           

    // Clock Divider
    clk_divider clk_div(.clk(clk), .slow_clk(slow_clk));

    // Convert binary to BCD
    bin2bcd bin_bcd_converter(
        .bin(output_data_0),
        .hundreds(hundreds), 
        .tens(tens),
        .ones(ones)
    );

    // 7-segment decoders for each digit
    hex_to_7seg hex_hundreds(.hex(hundreds), .seg(seg_hundreds));
    hex_to_7seg hex_tens(.hex(tens), .seg(seg_tens));
    hex_to_7seg hex_ones(.hex(ones), .seg(seg_ones));

     


    // **Separate Process for select_digit update**
    always @(posedge slow_clk) begin
        select_digit <= (select_digit + 1)%3;
    end

    // **Separate Process for Display Multiplexing**
   always @(*) begin
    case (select_digit)
        2'b00: begin
            an = 4'b1110; // Enable rightmost digit (ones)
            seg = seg_ones;
        end
        2'b01: begin
            an = 4'b1101; // Enable next digit (tens)
            seg = seg_tens;
        end
        2'b10: begin
            an = 4'b1011; // Enable next digit (hundreds)
            seg = seg_hundreds;
        end
        default: begin
            an = 4'b1111;
            seg = 7'b1111111;
        end
    endcase
    end
    assign slow_clk_o = slow_clk;
endmodule

seg_display_driver/seg_display_driver.srcs/sim_1/new/seg_display_driver_tb.v
`timescale 1ns / 1ps
//////////////////////////////////////////////////////////////////////////////////
// Company: 
// Engineer: 
// 
// Create Date: 03/01/2025 06:32:40 PM
// Design Name: 
// Module Name: seg_display_driver_tb
// Project Name: 
// Target Devices: 
// Tool Versions: 
// Description: 
// 
// Dependencies: 
// 
// Revision:
// Revision 0.01 - File Created
// Additional Comments:
// 
//////////////////////////////////////////////////////////////////////////////////


`timescale 1ps / 1ps

module seg_display_driver_tb;

    reg [7:0] output_data_0; // Input data for the display
    reg clk; // Clock signal
    wire [3:0] an; // Active digit select
    wire [6:0] seg; // 7-segment output


    // Instantiate the DUT (Device Under Test)
    seg_display_driver uut (
        .output_data_0(output_data_0),
        .clk(clk),
        .an(an),
        .seg(seg)
    );

    // Clock generation (50 MHz)
    always #1 clk = ~clk; // Toggle clock every 10ns (50MHz)

    initial begin
        $dumpfile("seg_display_driver_tb.vcd");  // Dump waveform data
        $dumpvars(0, seg_display_driver_tb);

        // Initialize signals
        clk = 0;
        output_data_0 = 8'd0; // Start with 0

        #100;
        output_data_0 = 8'd2; // Test 123 (multiplexing check)
        #100;
        output_data_0 = 8'd3; // Test 99
        #100;
        output_data_0 = 8'd4; // Test 45
        #100;
        output_data_0 = 8'd0; // Test 0

        $finish; // Stop simulation
    end

    // Monitor outputs
    initial begin
        $monitor("Time=%0t | output_data_0=%d | an=%b | seg=%b",
                 $time, output_data_0, an, seg);
    end

endmodule

seg_display_driver/seg_display_driver.sim/sim_1/behav/xsim/seg_display_driver_tb.vcd
$date
   Sun Mar  2 17:41:50 2025
$end

$version
  2024.2.0
  $dumpfile ("seg_display_driver_tb.vcd") 
$end

$timescale
  1ps
$end

$scope module seg_display_driver_tb $end
$var reg 8 ! output_data_0 [7:0] $end
$var reg 1 " clk $end
$var wire 4 # an [3:0] $end
$var wire 7 $ seg [6:0] $end
$scope module uut $end
$var wire 8 % output_data_0 [7:0] $end
$var wire 1 & clk $end
$var reg 4 ' an [3:0] $end
$var reg 7 ( seg [6:0] $end
$var wire 1 ) slow_clk $end
$var reg 2 * select_digit [1:0] $end
$var wire 7 + seg_hundreds [6:0] $end
$var wire 7 , seg_tens [6:0] $end
$var wire 7 - seg_ones [6:0] $end
$var wire 4 . hundreds [3:0] $end
$var wire 4 / tens [3:0] $end
$var wire 4 0 ones [3:0] $end
$var wire 1 1 slow_clk_o $end
$scope module clk_div $end
$var wire 1 & clk $end
$var wire 1 ) slow_clk $end
$var reg 17 2 count [16:0] $end
$upscope $end
$scope module bin_bcd_converter $end
$var wire 8 % bin [7:0] $end
$var wire 4 . hundreds [3:0] $end
$var wire 4 / tens [3:0] $end
$var wire 4 0 ones [3:0] $end
$var reg 12 3 bcd [11:0] $end
$var reg 4 4 i [3:0] $end
$upscope $end
$scope module hex_hundreds $end
$var wire 4 . hex [3:0] $end
$var reg 7 5 seg [6:0] $end
$upscope $end
$scope module hex_tens $end
$var wire 4 / hex [3:0] $end
$var reg 7 6 seg [6:0] $end
$upscope $end
$scope module hex_ones $end
$var wire 4 0 hex [3:0] $end
$var reg 7 7 seg [6:0] $end
$upscope $end
$upscope $end
$upscope $end
$enddefinitions $end

#0
$dumpvars
b0 !
0"
b1110 #
b1 $
b0 %
0&
b1110 '
b1 (
0)
b0 *
b1 +
b1 ,
b1 -
b0 .
b0 /
b0 0
01
b0 2
b0 3
b1000 4
b1 5
b1 6
b1 7
$end

#1
1"
1&
b1 2

#2
0"
0&

#3
1"
b1101 #
1&
b1101 '
1)
b1 *
11
b10 2

#4
0"
0&

#5
1"
1&
b11 2

#6
0"
0&

#7
1"
1&
0)
01
b100 2

#8
0"
0&

#9
1"
1&
b101 2

#10
0"
0&

#11
1"
b1011 #
1&
b1011 '
1)
b10 *
11
b110 2

#12
0"
0&

#13
1"
1&
b111 2

#14
0"
0&

#15
1"
1&
0)
01
b1000 2

#16
0"
0&

#17
1"
1&
b1001 2

#18
0"
0&

#19
1"
b1110 #
1&
b1110 '
1)
b0 *
11
b1010 2

#20
0"
0&

#21
1"
1&
b1011 2

#22
0"
0&

#23
1"
1&
0)
01
b1100 2

#24
0"
0&

#25
1"
1&
b1101 2

#26
0"
0&

#27
1"
b1101 #
1&
b1101 '
1)
b1 *
11
b1110 2

#28
0"
0&

#29
1"
1&
b1111 2

#30
0"
0&

#31
1"
1&
0)
01
b10000 2

#32
0"
0&

#33
1"
1&
b10001 2

#34
0"
0&

#35
1"
b1011 #
1&
b1011 '
1)
b10 *
11
b10010 2

#36
0"
0&

#37
1"
1&
b10011 2

#38
0"
0&

#39
1"
1&
0)
01
b10100 2

#40
0"
0&

#41
1"
1&
b10101 2

#42
0"
0&

#43
1"
b1110 #
1&
b1110 '
1)
b0 *
11
b10110 2

#44
0"
0&

#45
1"
1&
b10111 2

#46
0"
0&

#47
1"
1&
0)
01
b11000 2

#48
0"
0&

#49
1"
1&
b11001 2

#50
0"
0&

#51
1"
b1101 #
1&
b1101 '
1)
b1 *
11
b11010 2

#52
0"
0&

#53
1"
1&
b11011 2

#54
0"
0&

#55
1"
1&
0)
01
b11100 2

#56
0"
0&

#57
1"
1&
b11101 2

#58
0"
0&

#59
1"
b1011 #
1&
b1011 '
1)
b10 *
11
b11110 2

#60
0"
0&

#61
1"
1&
b11111 2

#62
0"
0&

#63
1"
1&
0)
01
b100000 2

#64
0"
0&

#65
1"
1&
b100001 2

#66
0"
0&

#67
1"
b1110 #
1&
b1110 '
1)
b0 *
11
b100010 2

#68
0"
0&

#69
1"
1&
b100011 2

#70
0"
0&

#71
1"
1&
0)
01
b100100 2

#72
0"
0&

#73
1"
1&
b100101 2

#74
0"
0&

#75
1"
b1101 #
1&
b1101 '
1)
b1 *
11
b100110 2

#76
0"
0&

#77
1"
1&
b100111 2

#78
0"
0&

#79
1"
1&
0)
01
b101000 2

#80
0"
0&

#81
1"
1&
b101001 2

#82
0"
0&

#83
1"
b1011 #
1&
b1011 '
1)
b10 *
11
b101010 2

#84
0"
0&

#85
1"
1&
b101011 2

#86
0"
0&

#87
1"
1&
0)
01
b101100 2

#88
0"
0&

#89
1"
1&
b101101 2

#90
0"
0&

#91
1"
b1110 #
1&
b1110 '
1)
b0 *
11
b101110 2

#92
0"
0&

#93
1"
1&
b101111 2

#94
0"
0&

#95
1"
1&
0)
01
b110000 2

#96
0"
0&

#97
1"
1&
b110001 2

#98
0"
0&

#99
1"
b1101 #
1&
b1101 '
1)
b1 *
11
b110010 2

#100
b10 !
0"
b10 %
0&
b10010 -
b10 0
b10 3
b1000 4
b10010 7

#101
1"
1&
b110011 2

#102
0"
0&

#103
1"
1&
0)
01
b110100 2

#104
0"
0&

#105
1"
1&
b110101 2

#106
0"
0&

#107
1"
b1011 #
1&
b1011 '
1)
b10 *
11
b110110 2

#108
0"
0&

#109
1"
1&
b110111 2

#110
0"
0&

#111
1"
1&
0)
01
b111000 2

#112
0"
0&

#113
1"
1&
b111001 2

#114
0"
0&

#115
1"
b1110 #
b10010 $
1&
b1110 '
b10010 (
1)
b0 *
11
b111010 2

#116
0"
0&

#117
1"
1&
b111011 2

#118
0"
0&

#119
1"
1&
0)
01
b111100 2

#120
0"
0&

#121
1"
1&
b111101 2

#122
0"
0&

#123
1"
b1101 #
b1 $
1&
b1101 '
b1 (
1)
b1 *
11
b111110 2

#124
0"
0&

#125
1"
1&
b111111 2

#126
0"
0&

#127
1"
1&
0)
01
b1000000 2

#128
0"
0&

#129
1"
1&
b1000001 2

#130
0"
0&

#131
1"
b1011 #
1&
b1011 '
1)
b10 *
11
b1000010 2

#132
0"
0&

#133
1"
1&
b1000011 2

#134
0"
0&

#135
1"
1&
0)
01
b1000100 2

#136
0"
0&

#137
1"
1&
b1000101 2

#138
0"
0&

#139
1"
b1110 #
b10010 $
1&
b1110 '
b10010 (
1)
b0 *
11
b1000110 2

#140
0"
0&

#141
1"
1&
b1000111 2

#142
0"
0&

#143
1"
1&
0)
01
b1001000 2

#144
0"
0&

#145
1"
1&
b1001001 2

#146
0"
0&

#147
1"
b1101 #
b1 $
1&
b1101 '
b1 (
1)
b1 *
11
b1001010 2

#148
0"
0&

#149
1"
1&
b1001011 2

#150
0"
0&

#151
1"
1&
0)
01
b1001100 2

#152
0"
0&

#153
1"
1&
b1001101 2

#154
0"
0&

#155
1"
b1011 #
1&
b1011 '
1)
b10 *
11
b1001110 2

#156
0"
0&

#157
1"
1&
b1001111 2

#158
0"
0&

#159
1"
1&
0)
01
b1010000 2

#160
0"
0&

#161
1"
1&
b1010001 2

#162
0"
0&

#163
1"
b1110 #
b10010 $
1&
b1110 '
b10010 (
1)
b0 *
11
b1010010 2

#164
0"
0&

#165
1"
1&
b1010011 2

#166
0"
0&

#167
1"
1&
0)
01
b1010100 2

#168
0"
0&

#169
1"
1&
b1010101 2

#170
0"
0&

#171
1"
b1101 #
b1 $
1&
b1101 '
b1 (
1)
b1 *
11
b1010110 2

#172
0"
0&

#173
1"
1&
b1010111 2

#174
0"
0&

#175
1"
1&
0)
01
b1011000 2

#176
0"
0&

#177
1"
1&
b1011001 2

#178
0"
0&

#179
1"
b1011 #
1&
b1011 '
1)
b10 *
11
b1011010 2

#180
0"
0&

#181
1"
1&
b1011011 2

#182
0"
0&

#183
1"
1&
0)
01
b1011100 2

#184
0"
0&

#185
1"
1&
b1011101 2

#186
0"
0&

#187
1"
b1110 #
b10010 $
1&
b1110 '
b10010 (
1)
b0 *
11
b1011110 2

#188
0"
0&

#189
1"
1&
b1011111 2

#190
0"
0&

#191
1"
1&
0)
01
b1100000 2

#192
0"
0&

#193
1"
1&
b1100001 2

#194
0"
0&

#195
1"
b1101 #
b1 $
1&
b1101 '
b1 (
1)
b1 *
11
b1100010 2

#196
0"
0&

#197
1"
1&
b1100011 2

#198
0"
0&

#199
1"
1&
0)
01
b1100100 2

#200
b11 !
0"
b11 %
0&
b110 -
b11 0
b11 3
b1000 4
b110 7

#201
1"
1&
b1100101 2

#202
0"
0&

#203
1"
b1011 #
1&
b1011 '
1)
b10 *
11
b1100110 2

#204
0"
0&

#205
1"
1&
b1100111 2

#206
0"
0&

#207
1"
1&
0)
01
b1101000 2

#208
0"
0&

#209
1"
1&
b1101001 2

#210
0"
0&

#211
1"
b1110 #
b110 $
1&
b1110 '
b110 (
1)
b0 *
11
b1101010 2

#212
0"
0&

#213
1"
1&
b1101011 2

#214
0"
0&

#215
1"
1&
0)
01
b1101100 2

#216
0"
0&

#217
1"
1&
b1101101 2

#218
0"
0&

#219
1"
b1101 #
b1 $
1&
b1101 '
b1 (
1)
b1 *
11
b1101110 2

#220
0"
0&

#221
1"
1&
b1101111 2

#222
0"
0&

#223
1"
1&
0)
01
b1110000 2

#224
0"
0&

#225
1"
1&
b1110001 2

#226
0"
0&

#227
1"
b1011 #
1&
b1011 '
1)
b10 *
11
b1110010 2

#228
0"
0&

#229
1"
1&
b1110011 2

#230
0"
0&

#231
1"
1&
0)
01
b1110100 2

#232
0"
0&

#233
1"
1&
b1110101 2

#234
0"
0&

#235
1"
b1110 #
b110 $
1&
b1110 '
b110 (
1)
b0 *
11
b1110110 2

#236
0"
0&

#237
1"
1&
b1110111 2

#238
0"
0&

#239
1"
1&
0)
01
b1111000 2

#240
0"
0&

#241
1"
1&
b1111001 2

#242
0"
0&

#243
1"
b1101 #
b1 $
1&
b1101 '
b1 (
1)
b1 *
11
b1111010 2

#244
0"
0&

#245
1"
1&
b1111011 2

#246
0"
0&

#247
1"
1&
0)
01
b1111100 2

#248
0"
0&

#249
1"
1&
b1111101 2

#250
0"
0&

#251
1"
b1011 #
1&
b1011 '
1)
b10 *
11
b1111110 2

#252
0"
0&

#253
1"
1&
b1111111 2

#254
0"
0&

#255
1"
1&
0)
01
b10000000 2

#256
0"
0&

#257
1"
1&
b10000001 2

#258
0"
0&

#259
1"
b1110 #
b110 $
1&
b1110 '
b110 (
1)
b0 *
11
b10000010 2

#260
0"
0&

#261
1"
1&
b10000011 2

#262
0"
0&

#263
1"
1&
0)
01
b10000100 2

#264
0"
0&

#265
1"
1&
b10000101 2

#266
0"
0&

#267
1"
b1101 #
b1 $
1&
b1101 '
b1 (
1)
b1 *
11
b10000110 2

#268
0"
0&

#269
1"
1&
b10000111 2

#270
0"
0&

#271
1"
1&
0)
01
b10001000 2

#272
0"
0&

#273
1"
1&
b10001001 2

#274
0"
0&

#275
1"
b1011 #
1&
b1011 '
1)
b10 *
11
b10001010 2

#276
0"
0&

#277
1"
1&
b10001011 2

#278
0"
0&

#279
1"
1&
0)
01
b10001100 2

#280
0"
0&

#281
1"
1&
b10001101 2

#282
0"
0&

#283
1"
b1110 #
b110 $
1&
b1110 '
b110 (
1)
b0 *
11
b10001110 2

#284
0"
0&

#285
1"
1&
b10001111 2

#286
0"
0&

#287
1"
1&
0)
01
b10010000 2

#288
0"
0&

#289
1"
1&
b10010001 2

#290
0"
0&

#291
1"
b1101 #
b1 $
1&
b1101 '
b1 (
1)
b1 *
11
b10010010 2

#292
0"
0&

#293
1"
1&
b10010011 2

#294
0"
0&

#295
1"
1&
0)
01
b10010100 2

#296
0"
0&

#297
1"
1&
b10010101 2

#298
0"
0&

#299
1"
b1011 #
1&
b1011 '
1)
b10 *
11
b10010110 2

#300
b100 !
0"
b100 %
0&
b1001100 -
b100 0
b100 3
b1000 4
b1001100 7

#301
1"
1&
b10010111 2

#302
0"
0&

#303
1"
1&
0)
01
b10011000 2

#304
0"
0&

#305
1"
1&
b10011001 2

#306
0"
0&

#307
1"
b1110 #
b1001100 $
1&
b1110 '
b1001100 (
1)
b0 *
11
b10011010 2

#308
0"
0&

#309
1"
1&
b10011011 2

#310
0"
0&

#311
1"
1&
0)
01
b10011100 2

#312
0"
0&

#313
1"
1&
b10011101 2

#314
0"
0&

#315
1"
b1101 #
b1 $
1&
b1101 '
b1 (
1)
b1 *
11
b10011110 2

#316
0"
0&

#317
1"
1&
b10011111 2

#318
0"
0&

#319
1"
1&
0)
01
b10100000 2

#320
0"
0&

#321
1"
1&
b10100001 2

#322
0"
0&

#323
1"
b1011 #
1&
b1011 '
1)
b10 *
11
b10100010 2

#324
0"
0&

#325
1"
1&
b10100011 2

#326
0"
0&

#327
1"
1&
0)
01
b10100100 2

#328
0"
0&

#329
1"
1&
b10100101 2

#330
0"
0&

#331
1"
b1110 #
b1001100 $
1&
b1110 '
b1001100 (
1)
b0 *
11
b10100110 2

#332
0"
0&

#333
1"
1&
b10100111 2

#334
0"
0&

#335
1"
1&
0)
01
b10101000 2

#336
0"
0&

#337
1"
1&
b10101001 2

#338
0"
0&

#339
1"
b1101 #
b1 $
1&
b1101 '
b1 (
1)
b1 *
11
b10101010 2

#340
0"
0&

#341
1"
1&
b10101011 2

#342
0"
0&

#343
1"
1&
0)
01
b10101100 2

#344
0"
0&

#345
1"
1&
b10101101 2

#346
0"
0&

#347
1"
b1011 #
1&
b1011 '
1)
b10 *
11
b10101110 2

#348
0"
0&

#349
1"
1&
b10101111 2

#350
0"
0&

#351
1"
1&
0)
01
b10110000 2

#352
0"
0&

#353
1"
1&
b10110001 2

#354
0"
0&

#355
1"
b1110 #
b1001100 $
1&
b1110 '
b1001100 (
1)
b0 *
11
b10110010 2

#356
0"
0&

#357
1"
1&
b10110011 2

#358
0"
0&

#359
1"
1&
0)
01
b10110100 2

#360
0"
0&

#361
1"
1&
b10110101 2

#362
0"
0&

#363
1"
b1101 #
b1 $
1&
b1101 '
b1 (
1)
b1 *
11
b10110110 2

#364
0"
0&

#365
1"
1&
b10110111 2

#366
0"
0&

#367
1"
1&
0)
01
b10111000 2

#368
0"
0&

#369
1"
1&
b10111001 2

#370
0"
0&

#371
1"
b1011 #
1&
b1011 '
1)
b10 *
11
b10111010 2

#372
0"
0&

#373
1"
1&
b10111011 2

#374
0"
0&

#375
1"
1&
0)
01
b10111100 2

#376
0"
0&

#377
1"
1&
b10111101 2

#378
0"
0&

#379
1"
b1110 #
b1001100 $
1&
b1110 '
b1001100 (
1)
b0 *
11
b10111110 2

#380
0"
0&

#381
1"
1&
b10111111 2

#382
0"
0&

#383
1"
1&
0)
01
b11000000 2

#384
0"
0&

#385
1"
1&
b11000001 2

#386
0"
0&

#387
1"
b1101 #
b1 $
1&
b1101 '
b1 (
1)
b1 *
11
b11000010 2

#388
0"
0&

#389
1"
1&
b11000011 2

#390
0"
0&

#391
1"
1&
0)
01
b11000100 2

#392
0"
0&

#393
1"
1&
b11000101 2

#394
0"
0&

#395
1"
b1011 #
1&
b1011 '
1)
b10 *
11
b11000110 2

#396
0"
0&

#397
1"
1&
b11000111 2

#398
0"
0&

#399
1"
1&
0)
01
b11001000 2

#400
b0 !
